servicecontainer/__init__.py
service_container-1.0.0.dist-info/LICENSE
service_container-1.0.0.dist-info/METADATA
service_container-1.0.0.dist-info/WHEEL
service_container-1.0.0.dist-info/top_level.txt
service_container-1.0.0.dist-info/RECORD
