Metadata-Version: 2.1
Name: service-container
Version: 1.0.0
Summary: Dependency injection container with parameters and transaction control.
Home-page: UNKNOWN
Author: Heureka.cz
Author-email: fialovi@heureka.cz
License: Apache 2.0
Platform: UNKNOWN
